{
  "type": "Feature",
  "properties": {
    "gn:admin1_code":"02",
    "gn:asciiname":"Santo Antonio",
    "gn:country_code":"ST",
    "gn:dem":53,
    "gn:feature_class":"P",
    "gn:feature_code":"PPL",
    "gn:name":"Santo Ant\u00f3nio",
    "gn:population":0,
    "gn:timezone":"Africa/Sao_Tome",
    "iso:country":"ST",
    "wof:name":"Santo Antonio",
    "wof:placetype":"locality"
},
  "geometry": {"coordinates":[6.73333,0.23333],"type":"Point"}
}