{
  "type": "Feature",
  "properties": {
    "gn:admin1_code":"01",
    "gn:asciiname":"Santa Isabel",
    "gn:country_code":"ST",
    "gn:dem":151,
    "gn:feature_class":"P",
    "gn:feature_code":"PPL",
    "gn:name":"Santa Isabel",
    "gn:population":0,
    "gn:timezone":"Africa/Sao_Tome",
    "iso:country":"ST",
    "wof:name":"Santa Isabel",
    "wof:placetype":"locality"
},
  "geometry": {"coordinates":[7.41534,1.64815],"type":"Point"}
}