{
  "type": "Feature",
  "properties": {
    "gn:admin1_code":"02",
    "gn:asciiname":"Boa Morte",
    "gn:country_code":"ST",
    "gn:dem":45,
    "gn:feature_class":"P",
    "gn:feature_code":"PPL",
    "gn:name":"Boa Morte",
    "gn:population":0,
    "gn:timezone":"Africa/Sao_Tome",
    "iso:country":"ST",
    "wof:name":"Boa Morte",
    "wof:placetype":"locality"
},
  "geometry": {"coordinates":[6.7199,0.33991],"type":"Point"}
}