{
  "type": "Feature",
  "properties": {
    "gn:admin1_code":"01",
    "gn:asciiname":"Abade",
    "gn:country_code":"ST",
    "gn:dem":222,
    "gn:feature_class":"P",
    "gn:feature_code":"PPL",
    "gn:name":"Abade",
    "gn:population":0,
    "gn:timezone":"Africa/Sao_Tome",
    "iso:country":"ST",
    "wof:name":"Abade",
    "wof:placetype":"locality"
},
  "geometry": {"coordinates":[7.45712,1.6248],"type":"Point"}
}