{
  "type": "Feature",
  "properties": {
    "gn:admin1_code":"02",
    "gn:asciiname":"Poiso Alto",
    "gn:country_code":"ST",
    "gn:dem":571,
    "gn:feature_class":"P",
    "gn:feature_code":"PPL",
    "gn:name":"Poiso Alto",
    "gn:population":0,
    "gn:timezone":"Africa/Sao_Tome",
    "iso:country":"ST",
    "wof:name":"Poiso Alto",
    "wof:placetype":"locality"
},
  "geometry": {"coordinates":[6.61667,0.33333],"type":"Point"}
}