{
  "type": "Feature",
  "properties": {
    "gn:admin1_code":"01",
    "gn:asciiname":"Montalegre",
    "gn:country_code":"ST",
    "gn:dem":155,
    "gn:feature_class":"P",
    "gn:feature_code":"PPL",
    "gn:name":"Montalegre",
    "gn:population":0,
    "gn:timezone":"Africa/Sao_Tome",
    "iso:country":"ST",
    "wof:name":"Montalegre",
    "wof:placetype":"locality"
},
  "geometry": {"coordinates":[7.38861,1.63318],"type":"Point"}
}