{
  "type": "Feature",
  "properties": {
    "gn:admin1_code":"01",
    "gn:asciiname":"Montalegre",
    "gn:country_code":"ST",
    "gn:dem":155,
    "gn:feature_class":"P",
    "gn:feature_code":"PPL",
    "gn:name":"Montalegre",
    "gn:population":0,
    "gn:timezone":"Africa/Sao_Tome",
    "iso:country":"ST",
    "name:bak_x_preferred":[
        "\u041c\u043e\u043d\u0442\u0430\u043b\u0435\u0433\u0440\u0438"
    ],
    "name:cat_x_preferred":[
        "Montalegre"
    ],
    "name:ceb_x_preferred":[
        "Montalegre"
    ],
    "name:deu_x_preferred":[
        "Montalegre"
    ],
    "name:eus_x_preferred":[
        "Montalegre"
    ],
    "name:fra_x_preferred":[
        "Montalegre"
    ],
    "name:gle_x_preferred":[
        "Montalegre"
    ],
    "name:glg_x_preferred":[
        "Montalegre"
    ],
    "name:ita_x_preferred":[
        "Montalegre"
    ],
    "name:msa_x_preferred":[
        "Montalegre"
    ],
    "name:mwl_x_preferred":[
        "Montalegre"
    ],
    "name:nld_x_preferred":[
        "Montalegre"
    ],
    "name:pol_x_preferred":[
        "Montalegre"
    ],
    "name:por_x_preferred":[
        "Montalegre"
    ],
    "name:rus_x_preferred":[
        "\u041c\u043e\u043d\u0442\u0430\u043b\u0435\u0433\u0440\u0438"
    ],
    "name:spa_x_preferred":[
        "Montalegre"
    ],
    "name:tur_x_preferred":[
        "Montalegre"
    ],
    "name:ukr_x_preferred":[
        "\u041c\u043e\u043d\u0442\u0430\u043b\u0435\u0433\u0440\u0435"
    ],
    "name:vie_x_preferred":[
        "Montalegre"
    ],
    "name:vol_x_preferred":[
        "Montalegre"
    ],
    "name:war_x_preferred":[
        "Montalegre"
    ],
    "name:zho_x_preferred":[
        "\u8499\u5854\u840a\u683c\u91cc"
    ],
    "wof:name":"Montalegre",
    "wof:placetype":"locality"
},
  "geometry": {"coordinates":[7.38861,1.63318],"type":"Point"}
}