{
  "type": "Feature",
  "properties": {
    "gn:admin1_code":"02",
    "gn:asciiname":"Graca",
    "gn:country_code":"ST",
    "gn:dem":259,
    "gn:feature_class":"P",
    "gn:feature_code":"PPL",
    "gn:name":"Gra\u00e7a",
    "gn:population":0,
    "gn:timezone":"Africa/Sao_Tome",
    "iso:country":"ST",
    "wof:name":"Graca",
    "wof:placetype":"locality"
},
  "geometry": {"coordinates":[6.48333,0.25],"type":"Point"}
}