{
  "type": "Feature",
  "properties": {
    "gn:admin1_code":"02",
    "gn:asciiname":"Mirante",
    "gn:country_code":"ST",
    "gn:dem":455,
    "gn:feature_class":"P",
    "gn:feature_code":"PPL",
    "gn:name":"Mirante",
    "gn:population":0,
    "gn:timezone":"Africa/Sao_Tome",
    "iso:country":"ST",
    "wof:name":"Mirante",
    "wof:placetype":"locality"
},
  "geometry": {"coordinates":[6.51667,0.25],"type":"Point"}
}