{
  "type": "Feature",
  "properties": {
    "gn:admin1_code":"02",
    "gn:asciiname":"Mirante",
    "gn:country_code":"ST",
    "gn:dem":455,
    "gn:feature_class":"P",
    "gn:feature_code":"PPL",
    "gn:name":"Mirante",
    "gn:population":0,
    "gn:timezone":"Africa/Sao_Tome",
    "iso:country":"ST",
    "name:bpy_x_preferred":[
        "\u09ae\u09bf\u09b0\u09be\u09a8\u09cd\u099f\u09c7"
    ],
    "name:ceb_x_preferred":[
        "Mirante"
    ],
    "name:epo_x_preferred":[
        "Mirante"
    ],
    "name:eus_x_preferred":[
        "Mirante"
    ],
    "name:fra_x_preferred":[
        "Mirante"
    ],
    "name:hye_x_preferred":[
        "\u0544\u056b\u0580\u0561\u0576\u057f\u056b"
    ],
    "name:ita_x_preferred":[
        "Mirante"
    ],
    "name:kat_x_preferred":[
        "\u10db\u10d8\u10e0\u10d0\u10dc\u10e2\u10d8"
    ],
    "name:kaz_x_preferred":[
        "\u041c\u0438\u0440\u0430\u043d\u0442\u0438"
    ],
    "name:mlg_x_preferred":[
        "Mirante"
    ],
    "name:nld_x_preferred":[
        "Mirante"
    ],
    "name:nor_x_preferred":[
        "Mirante"
    ],
    "name:pol_x_preferred":[
        "Mirante"
    ],
    "name:por_x_preferred":[
        "Mirante"
    ],
    "name:ron_x_preferred":[
        "Mirante"
    ],
    "name:rus_x_preferred":[
        "\u041c\u0438\u0440\u0430\u043d\u0442\u0438"
    ],
    "name:swe_x_preferred":[
        "Mirante"
    ],
    "name:vie_x_preferred":[
        "Mirante"
    ],
    "name:vol_x_preferred":[
        "Mirante"
    ],
    "name:war_x_preferred":[
        "Mirante"
    ],
    "name:zho_x_preferred":[
        "\u7c73\u5170\u8482"
    ],
    "wof:name":"Mirante",
    "wof:placetype":"locality"
},
  "geometry": {"coordinates":[6.51667,0.25],"type":"Point"}
}