{
  "type": "Feature",
  "properties": {
    "gn:admin1_code":"01",
    "gn:asciiname":"Costa e Silva",
    "gn:country_code":"ST",
    "gn:dem":130,
    "gn:feature_class":"P",
    "gn:feature_code":"PPL",
    "gn:name":"Costa e Silva",
    "gn:population":0,
    "gn:timezone":"Africa/Sao_Tome",
    "iso:country":"ST",
    "wof:name":"Costa e Silva",
    "wof:placetype":"locality"
},
  "geometry": {"coordinates":[7.34789,1.55955],"type":"Point"}
}