{
  "type": "Feature",
  "properties": {
    "gn:admin1_code":"02",
    "gn:asciiname":"Conde",
    "gn:country_code":"ST",
    "gn:dem":112,
    "gn:feature_class":"P",
    "gn:feature_code":"PPL",
    "gn:name":"Conde",
    "gn:population":0,
    "gn:timezone":"Africa/Sao_Tome",
    "iso:country":"ST",
    "name:cat_x_preferred":[
        "Conde"
    ],
    "name:ceb_x_preferred":[
        "Conde"
    ],
    "name:ita_x_preferred":[
        "Conde"
    ],
    "name:nld_x_preferred":[
        "Conde"
    ],
    "name:nor_x_preferred":[
        "Conde"
    ],
    "name:pol_x_preferred":[
        "Conde"
    ],
    "name:por_x_preferred":[
        "Conde"
    ],
    "name:spa_x_preferred":[
        "Conde"
    ],
    "name:swe_x_preferred":[
        "Conde"
    ],
    "name:vie_x_preferred":[
        "Conde"
    ],
    "name:vol_x_preferred":[
        "Conde"
    ],
    "wof:name":"Conde",
    "wof:placetype":"locality"
},
  "geometry": {"coordinates":[6.66422,0.37625],"type":"Point"}
}