{
  "type": "Feature",
  "properties": {
    "gn:admin1_code":"02",
    "gn:asciiname":"Santarem",
    "gn:country_code":"ST",
    "gn:dem":109,
    "gn:feature_class":"P",
    "gn:feature_code":"PPL",
    "gn:name":"Santar\u00e9m",
    "gn:population":0,
    "gn:timezone":"Africa/Sao_Tome",
    "iso:country":"ST",
    "wof:name":"Santarem",
    "wof:placetype":"locality"
},
  "geometry": {"coordinates":[6.68333,0.35],"type":"Point"}
}