{
  "type": "Feature",
  "properties": {
    "gn:admin1_code":"01",
    "gn:asciiname":"Pau Cavalo",
    "gn:country_code":"ST",
    "gn:dem":166,
    "gn:feature_class":"P",
    "gn:feature_code":"PPL",
    "gn:name":"Pau Cavalo",
    "gn:population":0,
    "gn:timezone":"Africa/Sao_Tome",
    "iso:country":"ST",
    "wof:name":"Pau Cavalo",
    "wof:placetype":"locality"
},
  "geometry": {"coordinates":[7.37981,1.64167],"type":"Point"}
}