{
  "type": "Feature",
  "properties": {
    "gn:admin1_code":"01",
    "gn:asciiname":"Praia Inhame",
    "gn:country_code":"ST",
    "gn:dem":190,
    "gn:feature_class":"P",
    "gn:feature_code":"PPL",
    "gn:name":"Praia Inhame",
    "gn:population":0,
    "gn:timezone":"Africa/Sao_Tome",
    "iso:country":"ST",
    "wof:name":"Praia Inhame",
    "wof:placetype":"locality"
},
  "geometry": {"coordinates":[7.42787,1.66289],"type":"Point"}
}