{
  "type": "Feature",
  "properties": {
    "gn:admin1_code":"02",
    "gn:asciiname":"Macambrara",
    "gn:cc2":"ST",
    "gn:country_code":"ST",
    "gn:dem":726,
    "gn:feature_class":"P",
    "gn:feature_code":"PPL",
    "gn:name":"Macambrar\u00e1",
    "gn:population":0,
    "gn:timezone":"Africa/Sao_Tome",
    "iso:country":"ST",
    "name:und_x_variant":[
        "Makambrar\u00e1",
        "Macambrar\u00e1"
    ],
    "wof:name":"Macambrara",
    "wof:placetype":"locality"
},
  "geometry": {"coordinates":[6.63333,0.26667],"type":"Point"}
}