{
  "type": "Feature",
  "properties": {
    "gn:admin1_code":"02",
    "gn:asciiname":"Praia da Rosema",
    "gn:country_code":"ST",
    "gn:dem":128,
    "gn:feature_class":"P",
    "gn:feature_code":"PPL",
    "gn:name":"Praia da Rosema",
    "gn:population":0,
    "gn:timezone":"Africa/Sao_Tome",
    "iso:country":"ST",
    "wof:name":"Praia da Rosema",
    "wof:placetype":"locality"
},
  "geometry": {"coordinates":[6.55911,0.35696],"type":"Point"}
}