{
  "type": "Feature",
  "properties": {
    "gn:admin1_code":"02",
    "gn:asciiname":"Quimpo",
    "gn:cc2":"ST",
    "gn:country_code":"ST",
    "gn:dem":129,
    "gn:feature_class":"P",
    "gn:feature_code":"PPL",
    "gn:name":"Quimpo",
    "gn:population":0,
    "gn:timezone":"Africa/Sao_Tome",
    "iso:country":"ST",
    "name:und_x_variant":[
        "Kimpo",
        "Quimpo"
    ],
    "wof:name":"Quimpo",
    "wof:placetype":"locality"
},
  "geometry": {"coordinates":[6.71667,0.25],"type":"Point"}
}