{
  "type": "Feature",
  "properties": {
    "gn:admin1_code":"02",
    "gn:asciiname":"Cantagalo",
    "gn:country_code":"ST",
    "gn:dem":263,
    "gn:feature_class":"P",
    "gn:feature_code":"PPL",
    "gn:name":"Cantagalo",
    "gn:population":0,
    "gn:timezone":"Africa/Sao_Tome",
    "iso:country":"ST",
    "name:cat_x_preferred":[
        "Cantagalo"
    ],
    "name:ceb_x_preferred":[
        "Cantagalo"
    ],
    "name:deu_x_preferred":[
        "Cantagalo"
    ],
    "name:ita_x_preferred":[
        "Cantagalo"
    ],
    "name:nld_x_preferred":[
        "Cantagalo"
    ],
    "name:nor_x_preferred":[
        "Cantagalo"
    ],
    "name:pol_x_preferred":[
        "Cantagalo"
    ],
    "name:por_x_preferred":[
        "Cantagalo"
    ],
    "name:rus_x_preferred":[
        "\u041a\u0430\u043d\u0442\u0430\u0433\u0430\u043b\u0443"
    ],
    "name:sco_x_preferred":[
        "Cantagalo"
    ],
    "name:swe_x_preferred":[
        "Cantagalo"
    ],
    "name:vol_x_preferred":[
        "Cantagalo"
    ],
    "name:war_x_preferred":[
        "Cantagalo"
    ],
    "wof:name":"Cantagalo",
    "wof:placetype":"locality"
},
  "geometry": {"coordinates":[6.68333,0.21667],"type":"Point"}
}