{
  "type": "Feature",
  "properties": {
    "gn:admin1_code":"01",
    "gn:asciiname":"Maquina",
    "gn:country_code":"ST",
    "gn:dem":156,
    "gn:feature_class":"P",
    "gn:feature_code":"PPL",
    "gn:name":"M\u00e1quina",
    "gn:population":0,
    "gn:timezone":"Africa/Sao_Tome",
    "iso:country":"ST",
    "wof:name":"Maquina",
    "wof:placetype":"locality"
},
  "geometry": {"coordinates":[7.38127,1.63541],"type":"Point"}
}