{
  "type": "Feature",
  "properties": {
    "gn:admin1_code":"01",
    "gn:asciiname":"Sao Mateus",
    "gn:country_code":"ST",
    "gn:dem":152,
    "gn:feature_class":"P",
    "gn:feature_code":"PPL",
    "gn:name":"S\u00e3o Mateus",
    "gn:population":0,
    "gn:timezone":"Africa/Sao_Tome",
    "iso:country":"ST",
    "wof:name":"Sao Mateus",
    "wof:placetype":"locality"
},
  "geometry": {"coordinates":[7.40259,1.63262],"type":"Point"}
}