{
  "type": "Feature",
  "properties": {
    "gn:admin1_code":"02",
    "gn:asciiname":"Bombon",
    "gn:country_code":"ST",
    "gn:dem":24,
    "gn:feature_class":"P",
    "gn:feature_code":"PPL",
    "gn:name":"Bombon",
    "gn:population":0,
    "gn:timezone":"Africa/Sao_Tome",
    "iso:country":"ST",
    "wof:name":"Bombon",
    "wof:placetype":"locality"
},
  "geometry": {"coordinates":[6.73333,0.31667],"type":"Point"}
}