{
  "type": "Feature",
  "properties": {
    "gn:admin1_code":"02",
    "gn:asciiname":"Bombon",
    "gn:country_code":"ST",
    "gn:dem":24,
    "gn:feature_class":"P",
    "gn:feature_code":"PPL",
    "gn:name":"Bombon",
    "gn:population":0,
    "gn:timezone":"Africa/Sao_Tome",
    "iso:country":"ST",
    "name:ceb_x_preferred":[
        "Bombon"
    ],
    "name:deu_x_preferred":[
        "Bombon"
    ],
    "name:fra_x_preferred":[
        "Bombon"
    ],
    "name:ita_x_preferred":[
        "Bombon"
    ],
    "name:jpn_x_preferred":[
        "\u30dc\u30f3\u30dc\u30f3"
    ],
    "name:nld_x_preferred":[
        "Bombon"
    ],
    "name:por_x_preferred":[
        "Bombon"
    ],
    "name:srp_x_preferred":[
        "\u0411\u043e\u043c\u0431\u043e\u043d"
    ],
    "name:war_x_preferred":[
        "Bombon"
    ],
    "wof:name":"Bombon",
    "wof:placetype":"locality"
},
  "geometry": {"coordinates":[6.73333,0.31667],"type":"Point"}
}