{
  "type": "Feature",
  "properties": {
    "gn:admin1_code":"02",
    "gn:asciiname":"Novo Brasil",
    "gn:cc2":"ST",
    "gn:country_code":"ST",
    "gn:dem":41,
    "gn:feature_class":"P",
    "gn:feature_code":"PPL",
    "gn:name":"Novo Brasil",
    "gn:population":0,
    "gn:timezone":"Africa/Sao_Tome",
    "iso:country":"ST",
    "name:und_x_variant":[
        "Novo Brazil",
        "Novo Brasil"
    ],
    "wof:name":"Novo Brasil",
    "wof:placetype":"locality"
},
  "geometry": {"coordinates":[6.56667,0.08333],"type":"Point"}
}