{
  "type": "Feature",
  "properties": {
    "gn:admin1_code":"02",
    "gn:asciiname":"Novo Brasil",
    "gn:cc2":"ST",
    "gn:country_code":"ST",
    "gn:dem":41,
    "gn:feature_class":"P",
    "gn:feature_code":"PPL",
    "gn:name":"Novo Brasil",
    "gn:population":0,
    "gn:timezone":"Africa/Sao_Tome",
    "iso:country":"ST",
    "name:bpy_x_preferred":[
        "\u09a8\u09cb\u09ad\u09cb \u09ac\u09cd\u09b0\u09be\u09b8\u09bf\u09b2"
    ],
    "name:ceb_x_preferred":[
        "Novo Brasil"
    ],
    "name:deu_x_preferred":[
        "Novo Brasil"
    ],
    "name:epo_x_preferred":[
        "Novo Brasil"
    ],
    "name:eus_x_preferred":[
        "Novo Brasil"
    ],
    "name:fra_x_preferred":[
        "Novo Brasil"
    ],
    "name:hye_x_preferred":[
        "\u0546\u0578\u057e\u0578\u0582 \u0532\u0580\u0561\u0566\u056b\u056c"
    ],
    "name:ita_x_preferred":[
        "Novo Brasil"
    ],
    "name:kat_x_preferred":[
        "\u10dc\u10dd\u10d5\u10e3-\u10d1\u10e0\u10d0\u10d6\u10d8\u10da\u10d8"
    ],
    "name:kaz_x_preferred":[
        "\u041d\u043e\u0432\u0443-\u0411\u0440\u0430\u0437\u0438\u043b"
    ],
    "name:mlg_x_preferred":[
        "Novo Brasil"
    ],
    "name:nld_x_preferred":[
        "Novo Brasil"
    ],
    "name:nor_x_preferred":[
        "Novo Brasil"
    ],
    "name:por_x_preferred":[
        "Novo Brasil"
    ],
    "name:ron_x_preferred":[
        "Novo Brasil"
    ],
    "name:rus_x_preferred":[
        "\u041d\u043e\u0432\u0443-\u0411\u0440\u0430\u0437\u0438\u043b"
    ],
    "name:spa_x_preferred":[
        "Novo Brasil"
    ],
    "name:swe_x_preferred":[
        "Novo Brasil"
    ],
    "name:und_x_variant":[
        "Novo Brazil",
        "Novo Brasil"
    ],
    "name:vie_x_preferred":[
        "Novo Brasil"
    ],
    "name:vol_x_preferred":[
        "Novo Brasil"
    ],
    "name:war_x_preferred":[
        "Novo Brasil"
    ],
    "name:zho_x_preferred":[
        "\u65b0\u5df4\u897f"
    ],
    "wof:name":"Novo Brasil",
    "wof:placetype":"locality"
},
  "geometry": {"coordinates":[6.56667,0.08333],"type":"Point"}
}