{
  "type": "Feature",
  "properties": {
    "gn:admin1_code":"02",
    "gn:asciiname":"Porto Algere",
    "gn:country_code":"ST",
    "gn:dem":21,
    "gn:feature_class":"P",
    "gn:feature_code":"PPL",
    "gn:name":"Porto Algere",
    "gn:population":0,
    "gn:timezone":"Africa/Sao_Tome",
    "iso:country":"ST",
    "wof:name":"Porto Algere",
    "wof:placetype":"locality"
},
  "geometry": {"coordinates":[6.53352,0.03455],"type":"Point"}
}