{
  "type": "Feature",
  "properties": {
    "gn:admin1_code":"02",
    "gn:asciiname":"Gumbela",
    "gn:country_code":"ST",
    "gn:dem":240,
    "gn:feature_class":"P",
    "gn:feature_code":"PPL",
    "gn:name":"Gumbela",
    "gn:population":0,
    "gn:timezone":"Africa/Sao_Tome",
    "iso:country":"ST",
    "wof:name":"Gumbela",
    "wof:placetype":"locality"
},
  "geometry": {"coordinates":[6.55,0.08333],"type":"Point"}
}